pydentic/__init__.py
pydentic/exceptions.py
pydentic/py.typed
pydentic/strings/__init__.py
pydentic-0.0.1.dev3.dist-info/LICENSE
pydentic-0.0.1.dev3.dist-info/METADATA
pydentic-0.0.1.dev3.dist-info/WHEEL
pydentic-0.0.1.dev3.dist-info/top_level.txt
pydentic-0.0.1.dev3.dist-info/RECORD
