Metadata-Version: 2.1
Name: pydentic
Version: 0.0.1.dev3
Summary: Pydantic Identifiers
Home-page: UNKNOWN
Author: Nuno André
Author-email: mail@nunoand.re
License: BSD-3-Clause
Project-URL: Source, https://github.com/nuno-andre/pydentic
Project-URL: Bug Tracker, https://github.com/nuno-andre/pydentic/issues
Platform: any
Requires-Python: >=3.6.1
Provides-Extra: dev
Provides-Extra: test
